roget/10681-body.py
roget/__init__.py
roget/roget_parser.py
RogetThesaurus-0.0.8.dist-info/LICENSE
RogetThesaurus-0.0.8.dist-info/METADATA
RogetThesaurus-0.0.8.dist-info/WHEEL
RogetThesaurus-0.0.8.dist-info/top_level.txt
RogetThesaurus-0.0.8.dist-info/RECORD
