Metadata-Version: 2.1
Name: RogetThesaurus
Version: 0.0.8
Summary: API to the Roget thesaurus
Home-page: https://github.com/MoserMichael/roget-thesaurus-parser
Author: Michael Moser
Author-email: moser.michael@gmail.com
License: BSD
Keywords: natural language processing; thesaurus
Platform: UNKNOWN
Classifier: Natural Language :: English
Classifier: Topic :: Text Processing :: Linguistic
Classifier: Intended Audience :: Science/Research
Classifier: Intended Audience :: Developers
Classifier: Operating System :: OS Independent
Classifier: License :: OSI Approved :: BSD License
Requires-Python: >=3.6
